{
  "$schema": "./latest.schema.json",
  "version": "0.3.0.0",
  "urls": {
    "windows":"https://github.com/adminclairvoyance/clairvoyance_update/releases/download/v0.4.1/Clairvoyance-v0.3.0-win-x64.zip",
    "macos":"",
    "linux":""
  },
  "mandatory": false,
  "release_notes": "1.We change the UI design and remove unnecessary content on the page. Current Monitor page look much more tidy and clean.\n2.We restructure algorithm of comm and improve the maintainability.\n3.From now on, CLairvoyance will be used in English.\n",
  "published_at": "2025-12-15T19:40:00"
}
